micrometa/__init__.py
micrometa/micrometa.py
micrometa/tools.py
tests/__init__.py
tests/tests/__init__.py
tests/tests/test_micrometa.py
tests/tests/test_tools.py
micrometa-0.0.11.dist-info/LICENSE
micrometa-0.0.11.dist-info/METADATA
micrometa-0.0.11.dist-info/WHEEL
micrometa-0.0.11.dist-info/top_level.txt
micrometa-0.0.11.dist-info/RECORD
